trl_jobs/__init__.py
trl_jobs/cli.py
trl_jobs/version.txt
trl_jobs/configs/Meta-Llama-3-8B-Instruct-a100-large-peft.yaml
trl_jobs/configs/Meta-Llama-3-8B-Instruct-a100-large.yaml
trl_jobs/configs/Meta-Llama-3-8B-a100-large-peft.yaml
trl_jobs/configs/Meta-Llama-3-8B-a100-large.yaml
trl_jobs/configs/Qwen3-0.6B-Base-a100-large.yaml
trl_jobs/configs/Qwen3-0.6B-a100-large.yaml
trl_jobs/configs/Qwen3-1.7B-Base-a100-large.yaml
trl_jobs/configs/Qwen3-1.7B-a100-large.yaml
trl_jobs/configs/Qwen3-14B-Base-a100-large-peft.yaml
trl_jobs/configs/Qwen3-14B-a100-large-peft.yaml
trl_jobs/configs/Qwen3-32B-a100-large-peft.yaml
trl_jobs/configs/Qwen3-4B-Base-a100-large.yaml
trl_jobs/configs/Qwen3-4B-a100-large.yaml
trl_jobs/configs/Qwen3-8B-Base-a100-large-peft.yaml
trl_jobs/configs/Qwen3-8B-Base-a100-large.yaml
trl_jobs/configs/Qwen3-8B-a100-large-peft.yaml
trl_jobs/configs/Qwen3-8B-a100-large.yaml
trl_jobs/configs/SmolLM3-3B-Base-a100-large.yaml
trl_jobs/configs/SmolLM3-3B-a100-large.yaml
trl_jobs-0.4.0.dist-info/METADATA
trl_jobs-0.4.0.dist-info/WHEEL
trl_jobs-0.4.0.dist-info/entry_points.txt
trl_jobs-0.4.0.dist-info/RECORD
