Metadata-Version: 2.4
Name: trl_jobs
Version: 0.4.0
Summary: TRL Jobs.
Project-URL: homepage, https://github.com/huggingface/trl-jobs
Project-URL: repository, https://github.com/huggingface/trl-jobs
Author-email: Quentin Gallouédec <quentin.gallouedec@huggingface.co>
Classifier: License :: OSI Approved :: MIT License
Classifier: Operating System :: OS Independent
Classifier: Programming Language :: Python :: 3
Requires-Python: >=3.10
Requires-Dist: huggingface-hub>=0.34.4
